aws_lambda/__init__.py
aws_lambda/aws_lambda.py
aws_lambda/helpers.py
aws_lambda/project_templates/config.yaml
aws_lambda/project_templates/event.json
aws_lambda/project_templates/service.py
python_lambda_dhe-1.0.0.data/scripts/lambda
tests/__init__.py
tests/dev_requirements.txt
tests/functional/__init__.py
tests/unit/__init__.py
tests/unit/test_LambdaContext.py
tests/unit/test_readHelper.py
python_lambda_dhe-1.0.0.dist-info/LICENSE
python_lambda_dhe-1.0.0.dist-info/METADATA
python_lambda_dhe-1.0.0.dist-info/WHEEL
python_lambda_dhe-1.0.0.dist-info/top_level.txt
python_lambda_dhe-1.0.0.dist-info/zip-safe
python_lambda_dhe-1.0.0.dist-info/RECORD
